pvaw/__init__.py
pvaw/constants.py
pvaw/make.py
pvaw/manufacturer.py
pvaw/results.py
pvaw/utils.py
pvaw/vin.py
pvaw/wmi.py
pvaw-0.0.3.dist-info/LICENSE.txt
pvaw-0.0.3.dist-info/METADATA
pvaw-0.0.3.dist-info/WHEEL
pvaw-0.0.3.dist-info/top_level.txt
pvaw-0.0.3.dist-info/RECORD
