Metadata-Version: 2.1
Name: pvaw
Version: 0.0.3
Summary: Python Wrapper for the NHTSA Vehicle API
Home-page: https://github.com/michaelmicheal/PythonVehicleAPIWrapper
Author: Michael Petro
Author-email: mgpetro99@gmail.com
License: UNKNOWN
Platform: UNKNOWN
Classifier: Programming Language :: Python :: 3
Classifier: License :: OSI Approved :: MIT License
Classifier: Operating System :: OS Independent
Requires-Python: >=3.6
Requires-Dist: pandas
Requires-Dist: requests
